[
  {
    "id": "bb622851-00c5-4909-93de-0f92b8410091",
    "data": [
      {
        "text": "restroom",
        "userDefined": false
      }
    ],
    "isTemplate": false,
    "count": 0
  },
  {
    "id": "1a9e2ab8-f8a1-4a1f-942f-f9e6fc1f5dc3",
    "data": [
      {
        "text": "can you tell me where the restroom is?",
        "userDefined": false
      }
    ],
    "isTemplate": false,
    "count": 0
  },
  {
    "id": "55636e56-9811-467f-9dc6-5a2b13adf94d",
    "data": [
      {
        "text": "Where is the restroom?",
        "userDefined": false
      }
    ],
    "isTemplate": false,
    "count": 0
  }
]